{
  "1": {
    "path": "2017/午後準備日（ネスト）/ゲート運搬/11.jpg"
  },
  "2": {
    "path": "2018/2018.9.6 執行部招集/5.jpg"
  },
  "3": {
    "path": "2018/2018.9.6 執行部招集/6.jpg"
  },
  "4": {
    "path": "2018/2018.9.6 執行部招集/7.jpg"
  },
  "5": {
    "path": "2018/2018.9.6 執行部招集/8.jpg"
  },
  "6": {
    "path": "2018/2018.9.10 パンフ写真など/3.jpg"
  },
  "7": {
    "path": "2018/2018.9.10 パンフ写真など/4.jpg"
  },
  "8": {
    "path": "2018/2018.9.10 パンフ写真など/5.jpg"
  },
  "9": {
    "path": "2018/2018.9.10 パンフ写真など/13.jpg"
  },
  "10": {
    "path": "2018/2018.9.10 パンフ写真など/24.jpg"
  },
  "11": {
    "path": "2018/2018.9.10 パンフ写真など/25.jpg"
  },
  "12": {
    "path": "2018/2018.9.10 パンフ写真など/26.jpg"
  },
  "13": {
    "path": "2018/2018.9.10 パンフ写真など/27.jpg"
  },
  "14": {
    "path": "2018/2018.9.10 パンフ写真など/28.jpg"
  },
  "15": {
    "path": "2018/2018.9.10 パンフ写真など/29.jpg"
  },
  "16": {
    "path": "2018/2018.9.10 パンフ写真など/30.jpg"
  },
  "17": {
    "path": "2018/2018.9.10 パンフ写真など/31.jpg"
  },
  "18": {
    "path": "2018/2018.9.10 パンフ写真など/32.jpg"
  },
  "19": {
    "path": "2018/2018.9.10 パンフ写真など/33.jpg"
  },
  "20": {
    "path": "2018/2018.9.10 パンフ写真など/34.jpg"
  },
  "21": {
    "path": "2018/2018.9.10 パンフ写真など/35.jpg"
  },
  "22": {
    "path": "2018/2018.9.10 パンフ写真など/36.jpg"
  },
  "23": {
    "path": "2018/2018.9.10 パンフ写真など/37.jpg"
  },
  "24": {
    "path": "2018/2018.9.10 パンフ写真など/38.jpg"
  },
  "25": {
    "path": "2018/2018.9.10 パンフ写真など/39.jpg"
  },
  "26": {
    "path": "2018/2018.9.10 パンフ写真など/40.jpg"
  },
  "27": {
    "path": "2018/2018.9.10 パンフ写真など/41.jpg"
  },
  "28": {
    "path": "2018/2018.9.10 パンフ写真など/42.jpg"
  },
  "29": {
    "path": "2018/2018.9.10 パンフ写真など/43.jpg"
  },
  "30": {
    "path": "2018/2018.9.10 パンフ写真など/44.jpg"
  },
  "31": {
    "path": "2018/2018.9.10 パンフ写真など/45.jpg"
  },
  "32": {
    "path": "2018/2018.9.10 パンフ写真など/46.jpg"
  },
  "33": {
    "path": "2018/2018.9.10 パンフ写真など/47.jpg"
  },
  "34": {
    "path": "2018/2018.9.10 パンフ写真など/48.jpg"
  },
  "35": {
    "path": "2018/2018.9.10 パンフ写真など/49.jpg"
  },
  "36": {
    "path": "2018/2018.9.10 パンフ写真など/50.jpg"
  },
  "37": {
    "path": "2018/2018.9.10 パンフ写真など/51.jpg"
  },
  "38": {
    "path": "2018/2018.9.10 パンフ写真など/52.jpg"
  },
  "39": {
    "path": "2018/2018.9.10 パンフ写真など/53.jpg"
  },
  "40": {
    "path": "2018/2018.9.10 パンフ写真など/54.jpg"
  },
  "41": {
    "path": "2018/2018.9.10 パンフ写真など/55.jpg"
  },
  "42": {
    "path": "2018/2018.9.10 パンフ写真など/56.jpg"
  },
  "43": {
    "path": "2018/2018.9.10 パンフ写真など/57.jpg"
  },
  "44": {
    "path": "2018/2018.9.10 パンフ写真など/58.jpg"
  },
  "45": {
    "path": "2018/2018.9.10 パンフ写真など/59.jpg"
  },
  "46": {
    "path": "2018/2018.9.10 パンフ写真など/60.jpg"
  },
  "47": {
    "path": "2018/2018.9.10 パンフ写真など/61.jpg"
  },
  "48": {
    "path": "2018/2018.9.10 パンフ写真など/62.jpg"
  },
  "49": {
    "path": "2018/2018.9.10 パンフ写真など/63.jpg"
  },
  "50": {
    "path": "2018/2018.9.10 パンフ写真など/64.jpg"
  },
  "51": {
    "path": "2018/2018.9.10 パンフ写真など/65.jpg"
  },
  "52": {
    "path": "2018/2018.9.10 パンフ写真など/66.jpg"
  },
  "53": {
    "path": "2018/2018.9.10 パンフ写真など/67.jpg"
  },
  "54": {
    "path": "2018/2018.9.10 パンフ写真など/68.jpg"
  },
  "55": {
    "path": "2018/2018.9.10 パンフ写真など/69.jpg"
  },
  "56": {
    "path": "2018/2018.9.10 パンフ写真など/70.jpg"
  },
  "57": {
    "path": "2018/2018.9.10 パンフ写真など/71.jpg"
  },
  "58": {
    "path": "2018/2018.9.10 パンフ写真など/72.jpg"
  },
  "59": {
    "path": "2018/2018.9.10 パンフ写真など/73.jpg"
  },
  "60": {
    "path": "2018/2018.9.10 パンフ写真など/74.jpg"
  },
  "61": {
    "path": "2018/2018.9.10 パンフ写真など/75.jpg"
  },
  "62": {
    "path": "2018/2018.9.10 パンフ写真など/76.jpg"
  },
  "63": {
    "path": "2018/2018.9.10 パンフ写真など/77.jpg"
  },
  "64": {
    "path": "2018/2018.9.10 パンフ写真など/78.jpg"
  },
  "65": {
    "path": "2018/2018.9.10 パンフ写真など/79.jpg"
  },
  "66": {
    "path": "2018/2018.9.10 パンフ写真など/80.jpg"
  },
  "67": {
    "path": "2018/2018.9.10 パンフ写真など/81.jpg"
  },
  "68": {
    "path": "2018/2018.9.10 パンフ写真など/82.jpg"
  },
  "69": {
    "path": "2018/2018.9.10 パンフ写真など/83.jpg"
  },
  "70": {
    "path": "2018/2018.9.10 パンフ写真など/84.jpg"
  },
  "71": {
    "path": "2018/2018.9.10 パンフ写真など/85.jpg"
  },
  "72": {
    "path": "2018/2018.9.10 パンフ写真など/86.jpg"
  },
  "73": {
    "path": "2018/2018.9.10 パンフ写真など/87.jpg"
  },
  "74": {
    "path": "2018/2018.9.10 パンフ写真など/88.jpg"
  },
  "75": {
    "path": "2018/2018.9.10 パンフ写真など/89.jpg"
  },
  "76": {
    "path": "2018/2018.9.10 パンフ写真など/90.jpg"
  },
  "77": {
    "path": "2018/2018.9.10 パンフ写真など/91.jpg"
  },
  "78": {
    "path": "2018/2018.9.10 パンフ写真など/92.jpg"
  },
  "79": {
    "path": "2018/2018.9.10 パンフ写真など/93.jpg"
  },
  "80": {
    "path": "2018/2018.9.10 パンフ写真など/94.jpg"
  },
  "81": {
    "path": "2018/2018.9.10 パンフ写真など/95.jpg"
  },
  "82": {
    "path": "2018/2018.9.10 パンフ写真など/96.jpg"
  },
  "83": {
    "path": "2018/2018.9.10 パンフ写真など/97.jpg"
  },
  "84": {
    "path": "2018/2018.9.10 パンフ写真など/98.jpg"
  },
  "85": {
    "path": "2018/2018.9.10 パンフ写真など/132.jpg"
  },
  "86": {
    "path": "2018/2018.9.10 パンフ写真など/133.jpg"
  },
  "87": {
    "path": "2018/2018.9.10 パンフ写真など/134.jpg"
  },
  "88": {
    "path": "2018/2018.9.10 パンフ写真など/167.jpg"
  },
  "89": {
    "path": "2018/2018.9.10 パンフ写真など/168.jpg"
  },
  "90": {
    "path": "2018/2018.9.10 パンフ写真など/169.jpg"
  },
  "91": {
    "path": "2018/2018.9.10 パンフ写真など/170.jpg"
  },
  "92": {
    "path": "2018/2018.9.10 パンフ写真など/171.jpg"
  },
  "93": {
    "path": "2018/2018.9.10 パンフ写真など/192.jpg"
  },
  "94": {
    "path": "2018/2018.9.10 パンフ写真など/193.jpg"
  },
  "95": {
    "path": "2018/2018.9.10 パンフ写真など/194.jpg"
  },
  "96": {
    "path": "2018/2018.9.10 パンフ写真など/214.jpg"
  },
  "97": {
    "path": "2018/2018.9.10 パンフ写真など/215.jpg"
  },
  "98": {
    "path": "2018/2018.9.10 パンフ写真など/216.jpg"
  },
  "99": {
    "path": "2018/2018.9.10 パンフ写真など/217.jpg"
  },
  "100": {
    "path": "2018/2018.9.10 パンフ写真など/218.jpg"
  },
  "101": {
    "path": "2018/2018.9.10 パンフ写真など/219.jpg"
  },
  "102": {
    "path": "2018/2018.9.10 パンフ写真など/220.jpg"
  },
  "103": {
    "path": "2018/2018.9.10 パンフ写真など/221.jpg"
  },
  "104": {
    "path": "2018/2018.9.10 パンフ写真など/222.jpg"
  },
  "105": {
    "path": "2018/2018.9.10 パンフ写真など/223.jpg"
  },
  "106": {
    "path": "2018/2018.9.10 パンフ写真など/224.jpg"
  },
  "107": {
    "path": "2018/2018.9.10 パンフ写真など/225.jpg"
  },
  "108": {
    "path": "2018/2018.9.10 パンフ写真など/226.jpg"
  },
  "109": {
    "path": "2018/2018.9.10 パンフ写真など/227.jpg"
  },
  "110": {
    "path": "2018/2018.9.10 パンフ写真など/228.jpg"
  },
  "111": {
    "path": "2018/2018.9.10 パンフ写真など/229.jpg"
  },
  "112": {
    "path": "2018/2018.9.10 パンフ写真など/230.jpg"
  },
  "113": {
    "path": "2018/2018.9.10 パンフ写真など/231.jpg"
  },
  "114": {
    "path": "2018/2018.9.10 パンフ写真など/232.jpg"
  },
  "115": {
    "path": "2018/2018.9.10 パンフ写真など/233.jpg"
  },
  "116": {
    "path": "2018/2018.9.10 パンフ写真など/234.jpg"
  },
  "117": {
    "path": "2018/2018.9.10 パンフ写真など/235.jpg"
  },
  "118": {
    "path": "2018/2018.9.18 執行部招集(当日役職発表)/11.jpg"
  },
  "119": {
    "path": "2018/2018.9.18 執行部招集(当日役職発表)/13.jpg"
  },
  "120": {
    "path": "2018/2018.9.18 執行部招集(当日役職発表)/14.jpg"
  },
  "121": {
    "path": "2018/2018.9.27 午後準備日（ネスト）/校内（午後準）/8.jpg"
  },
  "122": {
    "path": "2018/2018.9.27 午後準備日（ネスト）/校内（午後準）/9.jpg"
  },
  "123": {
    "path": "2018/2018.9.27 午後準備日（ネスト）/講堂/1.jpg"
  },
  "124": {
    "path": "2018/2018.9.27 午後準備日（ネスト）/講堂/2.jpg"
  },
  "125": {
    "path": "2018/2018.9.27 午後準備日（ネスト）/講堂/3.jpg"
  },
  "126": {
    "path": "2018/2018.9.27 午後準備日（ネスト）/講堂/4.jpg"
  },
  "127": {
    "path": "2018/2018.9.28 準備日（ネスト）/グラウンド（ネスト）（準備日）/ステージリハ/7.jpg"
  },
  "128": {
    "path": "2018/2018.9.28 準備日（ネスト）/グラウンド（ネスト）（準備日）/ステージリハ/8.jpg"
  },
  "129": {
    "path": "2018/2018.9.28 準備日（ネスト）/グラウンド（ネスト）（準備日）/ステージリハ/9.jpg"
  },
  "130": {
    "path": "2018/2018.9.28 準備日（ネスト）/グラウンド（ネスト）（準備日）/ステージリハ/10.jpg"
  },
  "131": {
    "path": "2018/2018.9.28 準備日（ネスト）/グラウンド（ネスト）（準備日）/その他（準備日）/30.jpg"
  },
  "132": {
    "path": "2018/2018.10.1 整理日/300.jpg"
  },
  "133": {
    "path": "2018/2018.10.1 整理日/321.jpg"
  },
  "134": {
    "path": "2018/2018.10.1 整理日/322.jpg"
  },
  "135": {
    "path": "2018/2018.10.1 整理日/323.jpg"
  },
  "136": {
    "path": "2018/2018.10.1 整理日/324.jpg"
  },
  "137": {
    "path": "2018/2018.10.1 整理日/562.jpg"
  },
  "138": {
    "path": "2018/2018.10.1 整理日/563.jpg"
  },
  "139": {
    "path": "2018/2018.10.1 整理日/624.jpg"
  },
  "140": {
    "path": "2018/2018.10.1 整理日/625.jpg"
  },
  "141": {
    "path": "2018/2018.10.1 整理日/626.jpg"
  },
  "142": {
    "path": "2018/2018.10.1 整理日/627.jpg"
  },
  "143": {
    "path": "2018/2018.10.1 整理日/635.jpg"
  },
  "144": {
    "path": "2018/2018.10.1 夢庵/62.jpg"
  }
}